bootstrap.py
buildout.cfg
setup.py
bootstrap/bootstrap.py
src/zc/__init__.py
src/zc.icp.egg-info/PKG-INFO
src/zc.icp.egg-info/SOURCES.txt
src/zc.icp.egg-info/dependency_links.txt
src/zc.icp.egg-info/not-zip-safe
src/zc.icp.egg-info/requires.txt
src/zc.icp.egg-info/top_level.txt
src/zc/icp/README.txt
src/zc/icp/__init__.py
src/zc/icp/datagram.txt
src/zc/icp/interfaces.py
src/zc/icp/tests.py
