Metadata-Version: 1.0
Name: zc.icp
Version: 1.0.0
Summary: Small, pluggable ICP (Internet Cache Protocol) server
Home-page: svn+ssh://svn.zope.com/repos/main/zc.icp
Author: Benji York
Author-email: benji@zope.com
License: ZPL 2.1
Platform: UNKNOWN
Classifier: License :: OSI Approved :: Zope Public License
Classifier: Programming Language :: Python
